kpds_api_test/__init__.py
kpds_api_test/config.py
kpds_api_test/kpds_api_test.py
kpds_api_test-1.0.dist-info/METADATA
kpds_api_test-1.0.dist-info/WHEEL
kpds_api_test-1.0.dist-info/top_level.txt
kpds_api_test-1.0.dist-info/RECORD
